[
  {
    "image": "https://cdn.download.ams.birds.cornell.edu/api/v2/asset/625607690/480"
  },
  {
    "image": "https://cdn.download.ams.birds.cornell.edu/api/v2/asset/624774856/480"
  },
  {
    "image": "https://cdn.download.ams.birds.cornell.edu/api/v2/asset/624774855/480"
  },
  {
    "image": "https://cdn.download.ams.birds.cornell.edu/api/v2/asset/624774854/480"
  },
  {
    "image": "https://cdn.download.ams.birds.cornell.edu/api/v2/asset/624774852/480"
  },
  {
    "image": "https://cdn.download.ams.birds.cornell.edu/api/v2/asset/624774849/480"
  },
  {
    "image": "https://cdn.download.ams.birds.cornell.edu/api/v2/asset/624774853/480"
  },
  {
    "image": "https://cdn.download.ams.birds.cornell.edu/api/v2/asset/624774850/480"
  },
  {
    "image": "https://cdn.download.ams.birds.cornell.edu/api/v2/asset/624774851/480"
  },
  {
    "image": "https://cdn.download.ams.birds.cornell.edu/api/v2/asset/624774857/480"
  },
  {
    "image": "https://cdn.download.ams.birds.cornell.edu/api/v2/asset/621817807/480"
  },
  {
    "image": "https://cdn.download.ams.birds.cornell.edu/api/v2/asset/620421944/480"
  },
  {
    "image": "https://cdn.download.ams.birds.cornell.edu/api/v2/asset/619346140/480"
  },
  {
    "image": "https://cdn.download.ams.birds.cornell.edu/api/v2/asset/619346135/480"
  },
  {
    "image": "https://cdn.download.ams.birds.cornell.edu/api/v2/asset/619346138/480"
  },
  {
    "image": "https://cdn.download.ams.birds.cornell.edu/api/v2/asset/619346134/480"
  },
  {
    "image": "https://cdn.download.ams.birds.cornell.edu/api/v2/asset/619346137/480"
  },
  {
    "image": "https://cdn.download.ams.birds.cornell.edu/api/v2/asset/619346136/480"
  },
  {
    "image": "https://cdn.download.ams.birds.cornell.edu/api/v2/asset/619346133/480"
  },
  {
    "image": "https://cdn.download.ams.birds.cornell.edu/api/v2/asset/619346046/480"
  },
  {
    "image": "https://cdn.download.ams.birds.cornell.edu/api/v2/asset/619346043/480"
  },
  {
    "image": "https://cdn.download.ams.birds.cornell.edu/api/v2/asset/619346044/480"
  },
  {
    "image": "https://cdn.download.ams.birds.cornell.edu/api/v2/asset/619346048/480"
  },
  {
    "image": "https://cdn.download.ams.birds.cornell.edu/api/v2/asset/619346045/480"
  },
  {
    "image": "https://cdn.download.ams.birds.cornell.edu/api/v2/asset/619346041/480"
  },
  {
    "image": "https://cdn.download.ams.birds.cornell.edu/api/v2/asset/619346040/480"
  },
  {
    "image": "https://cdn.download.ams.birds.cornell.edu/api/v2/asset/619346042/480"
  },
  {
    "image": "https://cdn.download.ams.birds.cornell.edu/api/v2/asset/619346039/480"
  },
  {
    "image": "https://cdn.download.ams.birds.cornell.edu/api/v2/asset/619346038/480"
  },
  {
    "image": "https://cdn.download.ams.birds.cornell.edu/api/v2/asset/619345853/480"
  },
  {
    "image": "https://cdn.download.ams.birds.cornell.edu/api/v2/asset/619345849/480"
  },
  {
    "image": "https://cdn.download.ams.birds.cornell.edu/api/v2/asset/619345848/480"
  },
  {
    "image": "https://cdn.download.ams.birds.cornell.edu/api/v2/asset/619345851/480"
  },
  {
    "image": "https://cdn.download.ams.birds.cornell.edu/api/v2/asset/619345840/480"
  },
  {
    "image": "https://cdn.download.ams.birds.cornell.edu/api/v2/asset/619345847/480"
  },
  {
    "image": "https://cdn.download.ams.birds.cornell.edu/api/v2/asset/619345843/480"
  },
  {
    "image": "https://cdn.download.ams.birds.cornell.edu/api/v2/asset/619345850/480"
  },
  {
    "image": "https://cdn.download.ams.birds.cornell.edu/api/v2/asset/619345839/480"
  },
  {
    "image": "https://cdn.download.ams.birds.cornell.edu/api/v2/asset/619345842/480"
  },
  {
    "image": "https://cdn.download.ams.birds.cornell.edu/api/v2/asset/619345846/480"
  },
  {
    "image": "https://cdn.download.ams.birds.cornell.edu/api/v2/asset/619345844/480"
  },
  {
    "image": "https://cdn.download.ams.birds.cornell.edu/api/v2/asset/619345845/480"
  },
  {
    "image": "https://cdn.download.ams.birds.cornell.edu/api/v2/asset/619345841/480"
  },
  {
    "image": "https://cdn.download.ams.birds.cornell.edu/api/v2/asset/619345838/480"
  },
  {
    "image": "https://cdn.download.ams.birds.cornell.edu/api/v2/asset/617631638/480"
  },
  {
    "image": "https://cdn.download.ams.birds.cornell.edu/api/v2/asset/617631632/480"
  },
  {
    "image": "https://cdn.download.ams.birds.cornell.edu/api/v2/asset/617631636/480"
  },
  {
    "image": "https://cdn.download.ams.birds.cornell.edu/api/v2/asset/617631633/480"
  },
  {
    "image": "https://cdn.download.ams.birds.cornell.edu/api/v2/asset/617631634/480"
  },
  {
    "image": "https://cdn.download.ams.birds.cornell.edu/api/v2/asset/617631637/480"
  },
  {
    "image": "https://cdn.download.ams.birds.cornell.edu/api/v2/asset/617631635/480"
  },
  {
    "image": "https://cdn.download.ams.birds.cornell.edu/api/v2/asset/617607732/480"
  },
  {
    "image": "https://cdn.download.ams.birds.cornell.edu/api/v2/asset/617607731/480"
  },
  {
    "image": "https://cdn.download.ams.birds.cornell.edu/api/v2/asset/617607730/480"
  },
  {
    "image": "https://cdn.download.ams.birds.cornell.edu/api/v2/asset/617607721/480"
  },
  {
    "image": "https://cdn.download.ams.birds.cornell.edu/api/v2/asset/617607720/480"
  },
  {
    "image": "https://cdn.download.ams.birds.cornell.edu/api/v2/asset/617607719/480"
  },
  {
    "image": "https://cdn.download.ams.birds.cornell.edu/api/v2/asset/616870783/480"
  },
  {
    "image": "https://cdn.download.ams.birds.cornell.edu/api/v2/asset/616870774/480"
  },
  {
    "image": "https://cdn.download.ams.birds.cornell.edu/api/v2/asset/616870758/480"
  },
  {
    "image": "https://cdn.download.ams.birds.cornell.edu/api/v2/asset/616830425/480"
  },
  {
    "image": "https://cdn.download.ams.birds.cornell.edu/api/v2/asset/616795651/480"
  },
  {
    "image": "https://cdn.download.ams.birds.cornell.edu/api/v2/asset/616795650/480"
  },
  {
    "image": "https://cdn.download.ams.birds.cornell.edu/api/v2/asset/616742579/480"
  },
  {
    "image": "https://cdn.download.ams.birds.cornell.edu/api/v2/asset/616731021/480"
  },
  {
    "image": "https://cdn.download.ams.birds.cornell.edu/api/v2/asset/616731020/480"
  },
  {
    "image": "https://cdn.download.ams.birds.cornell.edu/api/v2/asset/616137870/480"
  },
  {
    "image": "https://cdn.download.ams.birds.cornell.edu/api/v2/asset/616137869/480"
  },
  {
    "image": "https://cdn.download.ams.birds.cornell.edu/api/v2/asset/616137868/480"
  },
  {
    "image": "https://cdn.download.ams.birds.cornell.edu/api/v2/asset/615942306/480"
  },
  {
    "image": "https://cdn.download.ams.birds.cornell.edu/api/v2/asset/615942309/480"
  },
  {
    "image": "https://cdn.download.ams.birds.cornell.edu/api/v2/asset/615942308/480"
  },
  {
    "image": "https://cdn.download.ams.birds.cornell.edu/api/v2/asset/615942307/480"
  },
  {
    "image": "https://cdn.download.ams.birds.cornell.edu/api/v2/asset/615867410/480"
  },
  {
    "image": "https://cdn.download.ams.birds.cornell.edu/api/v2/asset/615867407/480"
  },
  {
    "image": "https://cdn.download.ams.birds.cornell.edu/api/v2/asset/615867406/480"
  },
  {
    "image": "https://cdn.download.ams.birds.cornell.edu/api/v2/asset/615867396/480"
  },
  {
    "image": "https://cdn.download.ams.birds.cornell.edu/api/v2/asset/615867394/480"
  },
  {
    "image": "https://cdn.download.ams.birds.cornell.edu/api/v2/asset/615867393/480"
  },
  {
    "image": "https://cdn.download.ams.birds.cornell.edu/api/v2/asset/615867360/480"
  },
  {
    "image": "https://cdn.download.ams.birds.cornell.edu/api/v2/asset/615867361/480"
  },
  {
    "image": "https://cdn.download.ams.birds.cornell.edu/api/v2/asset/615867352/480"
  },
  {
    "image": "https://cdn.download.ams.birds.cornell.edu/api/v2/asset/615867344/480"
  },
  {
    "image": "https://cdn.download.ams.birds.cornell.edu/api/v2/asset/615867345/480"
  },
  {
    "image": "https://cdn.download.ams.birds.cornell.edu/api/v2/asset/615867346/480"
  },
  {
    "image": "https://cdn.download.ams.birds.cornell.edu/api/v2/asset/615867334/480"
  },
  {
    "image": "https://cdn.download.ams.birds.cornell.edu/api/v2/asset/615867332/480"
  },
  {
    "image": "https://cdn.download.ams.birds.cornell.edu/api/v2/asset/615867330/480"
  },
  {
    "image": "https://cdn.download.ams.birds.cornell.edu/api/v2/asset/615867327/480"
  },
  {
    "image": "https://cdn.download.ams.birds.cornell.edu/api/v2/asset/615867328/480"
  },
  {
    "image": "https://cdn.download.ams.birds.cornell.edu/api/v2/asset/615867326/480"
  },
  {
    "image": "https://cdn.download.ams.birds.cornell.edu/api/v2/asset/615830675/480"
  },
  {
    "image": "https://cdn.download.ams.birds.cornell.edu/api/v2/asset/615614544/480"
  },
  {
    "image": "https://cdn.download.ams.birds.cornell.edu/api/v2/asset/615614530/480"
  },
  {
    "image": "https://cdn.download.ams.birds.cornell.edu/api/v2/asset/615614527/480"
  },
  {
    "image": "https://cdn.download.ams.birds.cornell.edu/api/v2/asset/614253833/480"
  },
  {
    "image": "https://cdn.download.ams.birds.cornell.edu/api/v2/asset/614253730/480"
  },
  {
    "image": "https://cdn.download.ams.birds.cornell.edu/api/v2/asset/613369602/480"
  },
  {
    "image": "https://cdn.download.ams.birds.cornell.edu/api/v2/asset/613369603/480"
  },
  {
    "image": "https://cdn.download.ams.birds.cornell.edu/api/v2/asset/613342506/480"
  },
  {
    "image": "https://cdn.download.ams.birds.cornell.edu/api/v2/asset/613342510/480"
  },
  {
    "image": "https://cdn.download.ams.birds.cornell.edu/api/v2/asset/613342505/480"
  },
  {
    "image": "https://cdn.download.ams.birds.cornell.edu/api/v2/asset/613342504/480"
  },
  {
    "image": "https://cdn.download.ams.birds.cornell.edu/api/v2/asset/613342511/480"
  },
  {
    "image": "https://cdn.download.ams.birds.cornell.edu/api/v2/asset/613342509/480"
  },
  {
    "image": "https://cdn.download.ams.birds.cornell.edu/api/v2/asset/613342503/480"
  },
  {
    "image": "https://cdn.download.ams.birds.cornell.edu/api/v2/asset/613342502/480"
  },
  {
    "image": "https://cdn.download.ams.birds.cornell.edu/api/v2/asset/613342507/480"
  },
  {
    "image": "https://cdn.download.ams.birds.cornell.edu/api/v2/asset/613342501/480"
  },
  {
    "image": "https://cdn.download.ams.birds.cornell.edu/api/v2/asset/612969357/480"
  },
  {
    "image": "https://cdn.download.ams.birds.cornell.edu/api/v2/asset/611254991/480"
  },
  {
    "image": "https://cdn.download.ams.birds.cornell.edu/api/v2/asset/611254989/480"
  },
  {
    "image": "https://cdn.download.ams.birds.cornell.edu/api/v2/asset/611254990/480"
  },
  {
    "image": "https://cdn.download.ams.birds.cornell.edu/api/v2/asset/611254992/480"
  },
  {
    "image": "https://cdn.download.ams.birds.cornell.edu/api/v2/asset/611141212/480"
  },
  {
    "image": "https://cdn.download.ams.birds.cornell.edu/api/v2/asset/609624486/480"
  },
  {
    "image": "https://cdn.download.ams.birds.cornell.edu/api/v2/asset/609287728/480"
  },
  {
    "image": "https://cdn.download.ams.birds.cornell.edu/api/v2/asset/609287729/480"
  },
  {
    "image": "https://cdn.download.ams.birds.cornell.edu/api/v2/asset/609287730/480"
  },
  {
    "image": "https://cdn.download.ams.birds.cornell.edu/api/v2/asset/606538681/480"
  },
  {
    "image": "https://cdn.download.ams.birds.cornell.edu/api/v2/asset/603713231/480"
  },
  {
    "image": "https://cdn.download.ams.birds.cornell.edu/api/v2/asset/603703791/480"
  },
  {
    "image": "https://cdn.download.ams.birds.cornell.edu/api/v2/asset/598775861/480"
  },
  {
    "image": "https://cdn.download.ams.birds.cornell.edu/api/v2/asset/584067021/480"
  },
  {
    "image": "https://cdn.download.ams.birds.cornell.edu/api/v2/asset/584067011/480"
  },
  {
    "image": "https://cdn.download.ams.birds.cornell.edu/api/v2/asset/576883851/480"
  },
  {
    "image": "https://cdn.download.ams.birds.cornell.edu/api/v2/asset/576882781/480"
  },
  {
    "image": "https://cdn.download.ams.birds.cornell.edu/api/v2/asset/556503041/480"
  },
  {
    "image": "https://cdn.download.ams.birds.cornell.edu/api/v2/asset/556503051/480"
  },
  {
    "image": "https://cdn.download.ams.birds.cornell.edu/api/v2/asset/556502671/480"
  },
  {
    "image": "https://cdn.download.ams.birds.cornell.edu/api/v2/asset/556502661/480"
  },
  {
    "image": "https://cdn.download.ams.birds.cornell.edu/api/v2/asset/556501631/480"
  },
  {
    "image": "https://cdn.download.ams.birds.cornell.edu/api/v2/asset/556501621/480"
  },
  {
    "image": "https://cdn.download.ams.birds.cornell.edu/api/v2/asset/556501341/480"
  },
  {
    "image": "https://cdn.download.ams.birds.cornell.edu/api/v2/asset/556500881/480"
  },
  {
    "image": "https://cdn.download.ams.birds.cornell.edu/api/v2/asset/554007621/480"
  },
  {
    "image": "https://cdn.download.ams.birds.cornell.edu/api/v2/asset/554007631/480"
  },
  {
    "image": "https://cdn.download.ams.birds.cornell.edu/api/v2/asset/554007601/480"
  },
  {
    "image": "https://cdn.download.ams.birds.cornell.edu/api/v2/asset/554007591/480"
  },
  {
    "image": "https://cdn.download.ams.birds.cornell.edu/api/v2/asset/552830721/480"
  },
  {
    "image": "https://cdn.download.ams.birds.cornell.edu/api/v2/asset/544926541/480"
  },
  {
    "image": "https://cdn.download.ams.birds.cornell.edu/api/v2/asset/544182601/480"
  },
  {
    "image": "https://cdn.download.ams.birds.cornell.edu/api/v2/asset/541604001/480"
  },
  {
    "image": "https://cdn.download.ams.birds.cornell.edu/api/v2/asset/541603771/480"
  },
  {
    "image": "https://cdn.download.ams.birds.cornell.edu/api/v2/asset/541603741/480"
  },
  {
    "image": "https://cdn.download.ams.birds.cornell.edu/api/v2/asset/541603681/480"
  },
  {
    "image": "https://cdn.download.ams.birds.cornell.edu/api/v2/asset/541561471/480"
  },
  {
    "image": "https://cdn.download.ams.birds.cornell.edu/api/v2/asset/541561381/480"
  },
  {
    "image": "https://cdn.download.ams.birds.cornell.edu/api/v2/asset/540117501/480"
  },
  {
    "image": "https://cdn.download.ams.birds.cornell.edu/api/v2/asset/540117491/480"
  },
  {
    "image": "https://cdn.download.ams.birds.cornell.edu/api/v2/asset/540117511/480"
  },
  {
    "image": "https://cdn.download.ams.birds.cornell.edu/api/v2/asset/537882171/480"
  },
  {
    "image": "https://cdn.download.ams.birds.cornell.edu/api/v2/asset/536262281/480"
  },
  {
    "image": "https://cdn.download.ams.birds.cornell.edu/api/v2/asset/536261881/480"
  },
  {
    "image": "https://cdn.download.ams.birds.cornell.edu/api/v2/asset/536261281/480"
  },
  {
    "image": "https://cdn.download.ams.birds.cornell.edu/api/v2/asset/536259991/480"
  },
  {
    "image": "https://cdn.download.ams.birds.cornell.edu/api/v2/asset/536256981/480"
  },
  {
    "image": "https://cdn.download.ams.birds.cornell.edu/api/v2/asset/536256251/480"
  },
  {
    "image": "https://cdn.download.ams.birds.cornell.edu/api/v2/asset/521837561/480"
  },
  {
    "image": "https://cdn.download.ams.birds.cornell.edu/api/v2/asset/516669841/480"
  },
  {
    "image": "https://cdn.download.ams.birds.cornell.edu/api/v2/asset/516669821/480"
  },
  {
    "image": "https://cdn.download.ams.birds.cornell.edu/api/v2/asset/516669801/480"
  },
  {
    "image": "https://cdn.download.ams.birds.cornell.edu/api/v2/asset/516669811/480"
  },
  {
    "image": "https://cdn.download.ams.birds.cornell.edu/api/v2/asset/516669791/480"
  },
  {
    "image": "https://cdn.download.ams.birds.cornell.edu/api/v2/asset/516669831/480"
  },
  {
    "image": "https://cdn.download.ams.birds.cornell.edu/api/v2/asset/512445821/480"
  },
  {
    "image": "https://cdn.download.ams.birds.cornell.edu/api/v2/asset/489993981/480"
  },
  {
    "image": "https://cdn.download.ams.birds.cornell.edu/api/v2/asset/489993671/480"
  },
  {
    "image": "https://cdn.download.ams.birds.cornell.edu/api/v2/asset/489993791/480"
  },
  {
    "image": "https://cdn.download.ams.birds.cornell.edu/api/v2/asset/489993661/480"
  },
  {
    "image": "https://cdn.download.ams.birds.cornell.edu/api/v2/asset/489993701/480"
  },
  {
    "image": "https://cdn.download.ams.birds.cornell.edu/api/v2/asset/489993641/480"
  },
  {
    "image": "https://cdn.download.ams.birds.cornell.edu/api/v2/asset/489993681/480"
  },
  {
    "image": "https://cdn.download.ams.birds.cornell.edu/api/v2/asset/489993651/480"
  },
  {
    "image": "https://cdn.download.ams.birds.cornell.edu/api/v2/asset/489993691/480"
  },
  {
    "image": "https://cdn.download.ams.birds.cornell.edu/api/v2/asset/489993741/480"
  },
  {
    "image": "https://cdn.download.ams.birds.cornell.edu/api/v2/asset/479749271/480"
  },
  {
    "image": "https://cdn.download.ams.birds.cornell.edu/api/v2/asset/479749261/480"
  },
  {
    "image": "https://cdn.download.ams.birds.cornell.edu/api/v2/asset/477540691/480"
  },
  {
    "image": "https://cdn.download.ams.birds.cornell.edu/api/v2/asset/477539661/480"
  },
  {
    "image": "https://cdn.download.ams.birds.cornell.edu/api/v2/asset/477538541/480"
  },
  {
    "image": "https://cdn.download.ams.birds.cornell.edu/api/v2/asset/473138031/480"
  },
  {
    "image": "https://cdn.download.ams.birds.cornell.edu/api/v2/asset/473133511/480"
  },
  {
    "image": "https://cdn.download.ams.birds.cornell.edu/api/v2/asset/473133521/480"
  },
  {
    "image": "https://cdn.download.ams.birds.cornell.edu/api/v2/asset/473133531/480"
  },
  {
    "image": "https://cdn.download.ams.birds.cornell.edu/api/v2/asset/471948301/480"
  },
  {
    "image": "https://cdn.download.ams.birds.cornell.edu/api/v2/asset/471948291/480"
  },
  {
    "image": "https://cdn.download.ams.birds.cornell.edu/api/v2/asset/471948281/480"
  },
  {
    "image": "https://cdn.download.ams.birds.cornell.edu/api/v2/asset/471948271/480"
  },
  {
    "image": "https://cdn.download.ams.birds.cornell.edu/api/v2/asset/471948261/480"
  },
  {
    "image": "https://cdn.download.ams.birds.cornell.edu/api/v2/asset/463725871/480"
  },
  {
    "image": "https://cdn.download.ams.birds.cornell.edu/api/v2/asset/463725851/480"
  },
  {
    "image": "https://cdn.download.ams.birds.cornell.edu/api/v2/asset/463725841/480"
  },
  {
    "image": "https://cdn.download.ams.birds.cornell.edu/api/v2/asset/460852661/480"
  },
  {
    "image": "https://cdn.download.ams.birds.cornell.edu/api/v2/asset/460852321/480"
  },
  {
    "image": "https://cdn.download.ams.birds.cornell.edu/api/v2/asset/460852281/480"
  },
  {
    "image": "https://cdn.download.ams.birds.cornell.edu/api/v2/asset/460852271/480"
  },
  {
    "image": "https://cdn.download.ams.birds.cornell.edu/api/v2/asset/443063221/480"
  },
  {
    "image": "https://cdn.download.ams.birds.cornell.edu/api/v2/asset/443062651/480"
  },
  {
    "image": "https://cdn.download.ams.birds.cornell.edu/api/v2/asset/443062381/480"
  },
  {
    "image": "https://cdn.download.ams.birds.cornell.edu/api/v2/asset/412897761/480"
  },
  {
    "image": "https://cdn.download.ams.birds.cornell.edu/api/v2/asset/412897751/480"
  },
  {
    "image": "https://cdn.download.ams.birds.cornell.edu/api/v2/asset/412897741/480"
  },
  {
    "image": "https://cdn.download.ams.birds.cornell.edu/api/v2/asset/412897721/480"
  },
  {
    "image": "https://cdn.download.ams.birds.cornell.edu/api/v2/asset/412878271/480"
  },
  {
    "image": "https://cdn.download.ams.birds.cornell.edu/api/v2/asset/412878261/480"
  },
  {
    "image": "https://cdn.download.ams.birds.cornell.edu/api/v2/asset/402912191/480"
  },
  {
    "image": "https://cdn.download.ams.birds.cornell.edu/api/v2/asset/402912181/480"
  },
  {
    "image": "https://cdn.download.ams.birds.cornell.edu/api/v2/asset/402912151/480"
  },
  {
    "image": "https://cdn.download.ams.birds.cornell.edu/api/v2/asset/402730151/480"
  },
  {
    "image": "https://cdn.download.ams.birds.cornell.edu/api/v2/asset/402730141/480"
  },
  {
    "image": "https://cdn.download.ams.birds.cornell.edu/api/v2/asset/402730131/480"
  },
  {
    "image": "https://cdn.download.ams.birds.cornell.edu/api/v2/asset/402730121/480"
  },
  {
    "image": "https://cdn.download.ams.birds.cornell.edu/api/v2/asset/402730111/480"
  },
  {
    "image": "https://cdn.download.ams.birds.cornell.edu/api/v2/asset/402730091/480"
  },
  {
    "image": "https://cdn.download.ams.birds.cornell.edu/api/v2/asset/402730081/480"
  },
  {
    "image": "https://cdn.download.ams.birds.cornell.edu/api/v2/asset/402270981/480"
  },
  {
    "image": "https://cdn.download.ams.birds.cornell.edu/api/v2/asset/402270971/480"
  },
  {
    "image": "https://cdn.download.ams.birds.cornell.edu/api/v2/asset/402270961/480"
  },
  {
    "image": "https://cdn.download.ams.birds.cornell.edu/api/v2/asset/402270951/480"
  },
  {
    "image": "https://cdn.download.ams.birds.cornell.edu/api/v2/asset/369762161/480"
  },
  {
    "image": "https://cdn.download.ams.birds.cornell.edu/api/v2/asset/369762121/480"
  },
  {
    "image": "https://cdn.download.ams.birds.cornell.edu/api/v2/asset/369762091/480"
  },
  {
    "image": "https://cdn.download.ams.birds.cornell.edu/api/v2/asset/369762081/480"
  },
  {
    "image": "https://cdn.download.ams.birds.cornell.edu/api/v2/asset/369761981/480"
  },
  {
    "image": "https://cdn.download.ams.birds.cornell.edu/api/v2/asset/369761931/480"
  },
  {
    "image": "https://cdn.download.ams.birds.cornell.edu/api/v2/asset/369761911/480"
  },
  {
    "image": "https://cdn.download.ams.birds.cornell.edu/api/v2/asset/369761881/480"
  },
  {
    "image": "https://cdn.download.ams.birds.cornell.edu/api/v2/asset/367706231/480"
  },
  {
    "image": "https://cdn.download.ams.birds.cornell.edu/api/v2/asset/367706221/480"
  },
  {
    "image": "https://cdn.download.ams.birds.cornell.edu/api/v2/asset/367706211/480"
  },
  {
    "image": "https://cdn.download.ams.birds.cornell.edu/api/v2/asset/367706201/480"
  },
  {
    "image": "https://cdn.download.ams.birds.cornell.edu/api/v2/asset/367706191/480"
  },
  {
    "image": "https://cdn.download.ams.birds.cornell.edu/api/v2/asset/367706181/480"
  },
  {
    "image": "https://cdn.download.ams.birds.cornell.edu/api/v2/asset/367706161/480"
  },
  {
    "image": "https://cdn.download.ams.birds.cornell.edu/api/v2/asset/365698371/480"
  },
  {
    "image": "https://cdn.download.ams.birds.cornell.edu/api/v2/asset/363869701/480"
  },
  {
    "image": "https://cdn.download.ams.birds.cornell.edu/api/v2/asset/363869691/480"
  },
  {
    "image": "https://cdn.download.ams.birds.cornell.edu/api/v2/asset/363869681/480"
  },
  {
    "image": "https://cdn.download.ams.birds.cornell.edu/api/v2/asset/363869671/480"
  },
  {
    "image": "https://cdn.download.ams.birds.cornell.edu/api/v2/asset/363869661/480"
  },
  {
    "image": "https://cdn.download.ams.birds.cornell.edu/api/v2/asset/352194271/480"
  },
  {
    "image": "https://cdn.download.ams.birds.cornell.edu/api/v2/asset/352193181/480"
  },
  {
    "image": "https://cdn.download.ams.birds.cornell.edu/api/v2/asset/352192931/480"
  },
  {
    "image": "https://cdn.download.ams.birds.cornell.edu/api/v2/asset/352192461/480"
  },
  {
    "image": "https://cdn.download.ams.birds.cornell.edu/api/v2/asset/349991961/480"
  },
  {
    "image": "https://cdn.download.ams.birds.cornell.edu/api/v2/asset/349991951/480"
  },
  {
    "image": "https://cdn.download.ams.birds.cornell.edu/api/v2/asset/349991941/480"
  },
  {
    "image": "https://cdn.download.ams.birds.cornell.edu/api/v2/asset/349991921/480"
  },
  {
    "image": "https://cdn.download.ams.birds.cornell.edu/api/v2/asset/349991911/480"
  },
  {
    "image": "https://cdn.download.ams.birds.cornell.edu/api/v2/asset/349991901/480"
  },
  {
    "image": "https://cdn.download.ams.birds.cornell.edu/api/v2/asset/348498441/480"
  },
  {
    "image": "https://cdn.download.ams.birds.cornell.edu/api/v2/asset/317278971/480"
  },
  {
    "image": "https://cdn.download.ams.birds.cornell.edu/api/v2/asset/264880241/480"
  },
  {
    "image": "https://cdn.download.ams.birds.cornell.edu/api/v2/asset/264615541/480"
  },
  {
    "image": "https://cdn.download.ams.birds.cornell.edu/api/v2/asset/264615531/480"
  },
  {
    "image": "https://cdn.download.ams.birds.cornell.edu/api/v2/asset/264601441/480"
  },
  {
    "image": "https://cdn.download.ams.birds.cornell.edu/api/v2/asset/264601431/480"
  },
  {
    "image": "https://cdn.download.ams.birds.cornell.edu/api/v2/asset/264601421/480"
  },
  {
    "image": "https://cdn.download.ams.birds.cornell.edu/api/v2/asset/264601411/480"
  },
  {
    "image": "https://cdn.download.ams.birds.cornell.edu/api/v2/asset/264601401/480"
  },
  {
    "image": "https://cdn.download.ams.birds.cornell.edu/api/v2/asset/264601391/480"
  },
  {
    "image": "https://cdn.download.ams.birds.cornell.edu/api/v2/asset/264601381/480"
  },
  {
    "image": "https://cdn.download.ams.birds.cornell.edu/api/v2/asset/255408651/480"
  },
  {
    "image": "https://cdn.download.ams.birds.cornell.edu/api/v2/asset/255408621/480"
  },
  {
    "image": "https://cdn.download.ams.birds.cornell.edu/api/v2/asset/255408611/480"
  },
  {
    "image": "https://cdn.download.ams.birds.cornell.edu/api/v2/asset/255408591/480"
  },
  {
    "image": "https://cdn.download.ams.birds.cornell.edu/api/v2/asset/255408551/480"
  },
  {
    "image": "https://cdn.download.ams.birds.cornell.edu/api/v2/asset/255408521/480"
  },
  {
    "image": "https://cdn.download.ams.birds.cornell.edu/api/v2/asset/255408511/480"
  },
  {
    "image": "https://cdn.download.ams.birds.cornell.edu/api/v2/asset/255408501/480"
  },
  {
    "image": "https://cdn.download.ams.birds.cornell.edu/api/v2/asset/233365551/480"
  },
  {
    "image": "https://cdn.download.ams.birds.cornell.edu/api/v2/asset/231148791/480"
  },
  {
    "image": "https://cdn.download.ams.birds.cornell.edu/api/v2/asset/227444601/480"
  },
  {
    "image": "https://cdn.download.ams.birds.cornell.edu/api/v2/asset/227444591/480"
  },
  {
    "image": "https://cdn.download.ams.birds.cornell.edu/api/v2/asset/227444581/480"
  },
  {
    "image": "https://cdn.download.ams.birds.cornell.edu/api/v2/asset/227444571/480"
  },
  {
    "image": "https://cdn.download.ams.birds.cornell.edu/api/v2/asset/227444551/480"
  },
  {
    "image": "https://cdn.download.ams.birds.cornell.edu/api/v2/asset/220530391/480"
  },
  {
    "image": "https://cdn.download.ams.birds.cornell.edu/api/v2/asset/220523731/480"
  },
  {
    "image": "https://cdn.download.ams.birds.cornell.edu/api/v2/asset/189437031/480"
  },
  {
    "image": "https://cdn.download.ams.birds.cornell.edu/api/v2/asset/183956511/480"
  },
  {
    "image": "https://cdn.download.ams.birds.cornell.edu/api/v2/asset/183956491/480"
  },
  {
    "image": "https://cdn.download.ams.birds.cornell.edu/api/v2/asset/183956481/480"
  },
  {
    "image": "https://cdn.download.ams.birds.cornell.edu/api/v2/asset/183956431/480"
  },
  {
    "image": "https://cdn.download.ams.birds.cornell.edu/api/v2/asset/183956401/480"
  },
  {
    "image": "https://cdn.download.ams.birds.cornell.edu/api/v2/asset/165122421/480"
  },
  {
    "image": "https://cdn.download.ams.birds.cornell.edu/api/v2/asset/165122391/480"
  },
  {
    "image": "https://cdn.download.ams.birds.cornell.edu/api/v2/asset/165122371/480"
  },
  {
    "image": "https://cdn.download.ams.birds.cornell.edu/api/v2/asset/165122351/480"
  },
  {
    "image": "https://cdn.download.ams.birds.cornell.edu/api/v2/asset/165031551/480"
  },
  {
    "image": "https://cdn.download.ams.birds.cornell.edu/api/v2/asset/165031521/480"
  },
  {
    "image": "https://cdn.download.ams.birds.cornell.edu/api/v2/asset/165031511/480"
  },
  {
    "image": "https://cdn.download.ams.birds.cornell.edu/api/v2/asset/164721731/480"
  },
  {
    "image": "https://cdn.download.ams.birds.cornell.edu/api/v2/asset/164721721/480"
  },
  {
    "image": "https://cdn.download.ams.birds.cornell.edu/api/v2/asset/164720901/480"
  },
  {
    "image": "https://cdn.download.ams.birds.cornell.edu/api/v2/asset/164720891/480"
  },
  {
    "image": "https://cdn.download.ams.birds.cornell.edu/api/v2/asset/164547171/480"
  },
  {
    "image": "https://cdn.download.ams.birds.cornell.edu/api/v2/asset/164299761/480"
  },
  {
    "image": "https://cdn.download.ams.birds.cornell.edu/api/v2/asset/164299701/480"
  },
  {
    "image": "https://cdn.download.ams.birds.cornell.edu/api/v2/asset/149943111/480"
  },
  {
    "image": "https://cdn.download.ams.birds.cornell.edu/api/v2/asset/149772581/480"
  },
  {
    "image": "https://cdn.download.ams.birds.cornell.edu/api/v2/asset/149772571/480"
  },
  {
    "image": "https://cdn.download.ams.birds.cornell.edu/api/v2/asset/149772561/480"
  },
  {
    "image": "https://cdn.download.ams.birds.cornell.edu/api/v2/asset/149772551/480"
  },
  {
    "image": "https://cdn.download.ams.birds.cornell.edu/api/v2/asset/131728871/480"
  },
  {
    "image": "https://cdn.download.ams.birds.cornell.edu/api/v2/asset/131728861/480"
  },
  {
    "image": "https://cdn.download.ams.birds.cornell.edu/api/v2/asset/128263641/480"
  },
  {
    "image": "https://cdn.download.ams.birds.cornell.edu/api/v2/asset/128263621/480"
  },
  {
    "image": "https://cdn.download.ams.birds.cornell.edu/api/v2/asset/128263611/480"
  },
  {
    "image": "https://cdn.download.ams.birds.cornell.edu/api/v2/asset/128263591/480"
  },
  {
    "image": "https://cdn.download.ams.birds.cornell.edu/api/v2/asset/128263581/480"
  },
  {
    "image": "https://cdn.download.ams.birds.cornell.edu/api/v2/asset/126916931/480"
  },
  {
    "image": "https://cdn.download.ams.birds.cornell.edu/api/v2/asset/121480761/480"
  },
  {
    "image": "https://cdn.download.ams.birds.cornell.edu/api/v2/asset/121431581/480"
  },
  {
    "image": "https://cdn.download.ams.birds.cornell.edu/api/v2/asset/121002281/480"
  },
  {
    "image": "https://cdn.download.ams.birds.cornell.edu/api/v2/asset/113408751/480"
  },
  {
    "image": "https://cdn.download.ams.birds.cornell.edu/api/v2/asset/113408741/480"
  },
  {
    "image": "https://cdn.download.ams.birds.cornell.edu/api/v2/asset/113408721/480"
  },
  {
    "image": "https://cdn.download.ams.birds.cornell.edu/api/v2/asset/113408681/480"
  },
  {
    "image": "https://cdn.download.ams.birds.cornell.edu/api/v2/asset/96309851/480"
  },
  {
    "image": "https://cdn.download.ams.birds.cornell.edu/api/v2/asset/84056061/480"
  },
  {
    "image": "https://cdn.download.ams.birds.cornell.edu/api/v2/asset/80803601/480"
  },
  {
    "image": "https://cdn.download.ams.birds.cornell.edu/api/v2/asset/63364211/480"
  },
  {
    "image": "https://cdn.download.ams.birds.cornell.edu/api/v2/asset/63364201/480"
  },
  {
    "image": "https://cdn.download.ams.birds.cornell.edu/api/v2/asset/63364191/480"
  },
  {
    "image": "https://cdn.download.ams.birds.cornell.edu/api/v2/asset/63364181/480"
  },
  {
    "image": "https://cdn.download.ams.birds.cornell.edu/api/v2/asset/59802111/480"
  },
  {
    "image": "https://cdn.download.ams.birds.cornell.edu/api/v2/asset/48195741/480"
  },
  {
    "image": "https://cdn.download.ams.birds.cornell.edu/api/v2/asset/30492071/480"
  },
  {
    "image": "https://cdn.download.ams.birds.cornell.edu/api/v2/asset/30475711/480"
  },
  {
    "image": "https://cdn.download.ams.birds.cornell.edu/api/v2/asset/30475701/480"
  },
  {
    "image": "https://cdn.download.ams.birds.cornell.edu/api/v2/asset/29885311/480"
  },
  {
    "image": "https://cdn.download.ams.birds.cornell.edu/api/v2/asset/29885291/480"
  },
  {
    "image": "https://cdn.download.ams.birds.cornell.edu/api/v2/asset/29051451/480"
  },
  {
    "image": "https://cdn.download.ams.birds.cornell.edu/api/v2/asset/26033841/480"
  },
  {
    "image": "https://cdn.download.ams.birds.cornell.edu/api/v2/asset/25720101/480"
  },
  {
    "image": "https://cdn.download.ams.birds.cornell.edu/api/v2/asset/25719951/480"
  },
  {
    "image": "https://cdn.download.ams.birds.cornell.edu/api/v2/asset/25483571/480"
  },
  {
    "image": "https://cdn.download.ams.birds.cornell.edu/api/v2/asset/25483561/480"
  },
  {
    "image": "https://cdn.download.ams.birds.cornell.edu/api/v2/asset/25483551/480"
  },
  {
    "image": "https://cdn.download.ams.birds.cornell.edu/api/v2/asset/25483541/480"
  },
  {
    "image": "https://cdn.download.ams.birds.cornell.edu/api/v2/asset/22139141/480"
  }
]